dogweb/ static/style.css
dogweb/ templates/base.html
dogweb/ templates/index.html
dogweb/__init__.py
dogweb/app.py
dogweb-0.1.6.dist-info/METADATA
dogweb-0.1.6.dist-info/WHEEL
dogweb-0.1.6.dist-info/RECORD
