Metadata-Version: 2.1
Name: Dogweb
Version: 0.1.6
Summary: O DogWeb é um framework web minimalista desenvolvido em Python.
Author: Bruno Ragner
Author-email: brunooragnner@gmail.com
Requires-Python: >=3.8,<4.0
Classifier: Programming Language :: Python :: 3
Classifier: Programming Language :: Python :: 3.8
Classifier: Programming Language :: Python :: 3.9
Classifier: Programming Language :: Python :: 3.10
Classifier: Programming Language :: Python :: 3.11
Requires-Dist: jinja2 (>=2.11,<3.0)
Requires-Dist: werkzeug (>=2.0,<3.0)
